{"nodes": [{"id": "skills_video_downloader_scripts_download_video_py", "label": "download_video.py", "file_type": "code", "source_file": "skills\\video-downloader\\scripts\\download_video.py", "source_location": "L1"}, {"id": "download_video_check_yt_dlp", "label": "check_yt_dlp()", "file_type": "code", "source_file": "skills\\video-downloader\\scripts\\download_video.py", "source_location": "L13"}, {"id": "download_video_get_video_info", "label": "get_video_info()", "file_type": "code", "source_file": "skills\\video-downloader\\scripts\\download_video.py", "source_location": "L22"}, {"id": "download_video_download_video", "label": "download_video()", "file_type": "code", "source_file": "skills\\video-downloader\\scripts\\download_video.py", "source_location": "L33"}, {"id": "download_video_main", "label": "main()", "file_type": "code", "source_file": "skills\\video-downloader\\scripts\\download_video.py", "source_location": "L103"}, {"id": "download_video_rationale_14", "label": "Check if yt-dlp is installed, install if not.", "file_type": "rationale", "source_file": "skills\\video-downloader\\scripts\\download_video.py", "source_location": "L14"}, {"id": "download_video_rationale_23", "label": "Get information about the video without downloading.", "file_type": "rationale", "source_file": "skills\\video-downloader\\scripts\\download_video.py", "source_location": "L23"}, {"id": "download_video_rationale_34", "label": "Download a YouTube video.          Args:         url: YouTube video URL", "file_type": "rationale", "source_file": "skills\\video-downloader\\scripts\\download_video.py", "source_location": "L34"}], "edges": [{"source": "skills_video_downloader_scripts_download_video_py", "target": "argparse", "relation": "imports", "confidence": "EXTRACTED", "source_file": "skills\\video-downloader\\scripts\\download_video.py", "source_location": "L7", "weight": 1.0}, {"source": "skills_video_downloader_scripts_download_video_py", "target": "sys", "relation": "imports", "confidence": "EXTRACTED", "source_file": "skills\\video-downloader\\scripts\\download_video.py", "source_location": "L8", "weight": 1.0}, {"source": "skills_video_downloader_scripts_download_video_py", "target": "subprocess", "relation": "imports", "confidence": "EXTRACTED", "source_file": "skills\\video-downloader\\scripts\\download_video.py", "source_location": "L9", "weight": 1.0}, {"source": "skills_video_downloader_scripts_download_video_py", "target": "json", "relation": "imports", "confidence": "EXTRACTED", "source_file": "skills\\video-downloader\\scripts\\download_video.py", "source_location": "L10", "weight": 1.0}, {"source": "skills_video_downloader_scripts_download_video_py", "target": "download_video_check_yt_dlp", "relation": "contains", "confidence": "EXTRACTED", "source_file": "skills\\video-downloader\\scripts\\download_video.py", "source_location": "L13", "weight": 1.0}, {"source": "skills_video_downloader_scripts_download_video_py", "target": "download_video_get_video_info", "relation": "contains", "confidence": "EXTRACTED", "source_file": "skills\\video-downloader\\scripts\\download_video.py", "source_location": "L22", "weight": 1.0}, {"source": "skills_video_downloader_scripts_download_video_py", "target": "download_video_download_video", "relation": "contains", "confidence": "EXTRACTED", "source_file": "skills\\video-downloader\\scripts\\download_video.py", "source_location": "L33", "weight": 1.0}, {"source": "skills_video_downloader_scripts_download_video_py", "target": "download_video_main", "relation": "contains", "confidence": "EXTRACTED", "source_file": "skills\\video-downloader\\scripts\\download_video.py", "source_location": "L103", "weight": 1.0}, {"source": "download_video_download_video", "target": "download_video_check_yt_dlp", "relation": "calls", "confidence": "EXTRACTED", "source_file": "skills\\video-downloader\\scripts\\download_video.py", "source_location": "L44", "weight": 1.0}, {"source": "download_video_download_video", "target": "download_video_get_video_info", "relation": "calls", "confidence": "EXTRACTED", "source_file": "skills\\video-downloader\\scripts\\download_video.py", "source_location": "L86", "weight": 1.0}, {"source": "download_video_main", "target": "download_video_download_video", "relation": "calls", "confidence": "EXTRACTED", "source_file": "skills\\video-downloader\\scripts\\download_video.py", "source_location": "L133", "weight": 1.0}, {"source": "download_video_rationale_14", "target": "download_video_check_yt_dlp", "relation": "rationale_for", "confidence": "EXTRACTED", "source_file": "skills\\video-downloader\\scripts\\download_video.py", "source_location": "L14", "weight": 1.0}, {"source": "download_video_rationale_23", "target": "download_video_get_video_info", "relation": "rationale_for", "confidence": "EXTRACTED", "source_file": "skills\\video-downloader\\scripts\\download_video.py", "source_location": "L23", "weight": 1.0}, {"source": "download_video_rationale_34", "target": "download_video_download_video", "relation": "rationale_for", "confidence": "EXTRACTED", "source_file": "skills\\video-downloader\\scripts\\download_video.py", "source_location": "L34", "weight": 1.0}], "raw_calls": [{"caller_nid": "download_video_check_yt_dlp", "callee": "run", "source_file": "skills\\video-downloader\\scripts\\download_video.py", "source_location": "L16"}, {"caller_nid": "download_video_check_yt_dlp", "callee": "print", "source_file": "skills\\video-downloader\\scripts\\download_video.py", "source_location": "L18"}, {"caller_nid": "download_video_check_yt_dlp", "callee": "run", "source_file": "skills\\video-downloader\\scripts\\download_video.py", "source_location": "L19"}, {"caller_nid": "download_video_get_video_info", "callee": "run", "source_file": "skills\\video-downloader\\scripts\\download_video.py", "source_location": "L24"}, {"caller_nid": "download_video_get_video_info", "callee": "loads", "source_file": "skills\\video-downloader\\scripts\\download_video.py", "source_location": "L30"}, {"caller_nid": "download_video_download_video", "callee": "extend", "source_file": "skills\\video-downloader\\scripts\\download_video.py", "source_location": "L50"}, {"caller_nid": "download_video_download_video", "callee": "replace", "source_file": "skills\\video-downloader\\scripts\\download_video.py", "source_location": "L63"}, {"caller_nid": "download_video_download_video", "callee": "extend", "source_file": "skills\\video-downloader\\scripts\\download_video.py", "source_location": "L66"}, {"caller_nid": "download_video_download_video", "callee": "extend", "source_file": "skills\\video-downloader\\scripts\\download_video.py", "source_location": "L72"}, {"caller_nid": "download_video_download_video", "callee": "append", "source_file": "skills\\video-downloader\\scripts\\download_video.py", "source_location": "L77"}, {"caller_nid": "download_video_download_video", "callee": "print", "source_file": "skills\\video-downloader\\scripts\\download_video.py", "source_location": "L79"}, {"caller_nid": "download_video_download_video", "callee": "print", "source_file": "skills\\video-downloader\\scripts\\download_video.py", "source_location": "L80"}, {"caller_nid": "download_video_download_video", "callee": "print", "source_file": "skills\\video-downloader\\scripts\\download_video.py", "source_location": "L81"}, {"caller_nid": "download_video_download_video", "callee": "print", "source_file": "skills\\video-downloader\\scripts\\download_video.py", "source_location": "L82"}, {"caller_nid": "download_video_download_video", "callee": "print", "source_file": "skills\\video-downloader\\scripts\\download_video.py", "source_location": "L87"}, {"caller_nid": "download_video_download_video", "callee": "get", "source_file": "skills\\video-downloader\\scripts\\download_video.py", "source_location": "L87"}, {"caller_nid": "download_video_download_video", "callee": "print", "source_file": "skills\\video-downloader\\scripts\\download_video.py", "source_location": "L88"}, {"caller_nid": "download_video_download_video", "callee": "get", "source_file": "skills\\video-downloader\\scripts\\download_video.py", "source_location": "L88"}, {"caller_nid": "download_video_download_video", "callee": "get", "source_file": "skills\\video-downloader\\scripts\\download_video.py", "source_location": "L88"}, {"caller_nid": "download_video_download_video", "callee": "print", "source_file": "skills\\video-downloader\\scripts\\download_video.py", "source_location": "L89"}, {"caller_nid": "download_video_download_video", "callee": "get", "source_file": "skills\\video-downloader\\scripts\\download_video.py", "source_location": "L89"}, {"caller_nid": "download_video_download_video", "callee": "run", "source_file": "skills\\video-downloader\\scripts\\download_video.py", "source_location": "L92"}, {"caller_nid": "download_video_download_video", "callee": "print", "source_file": "skills\\video-downloader\\scripts\\download_video.py", "source_location": "L93"}, {"caller_nid": "download_video_download_video", "callee": "print", "source_file": "skills\\video-downloader\\scripts\\download_video.py", "source_location": "L96"}, {"caller_nid": "download_video_download_video", "callee": "print", "source_file": "skills\\video-downloader\\scripts\\download_video.py", "source_location": "L99"}, {"caller_nid": "download_video_main", "callee": "ArgumentParser", "source_file": "skills\\video-downloader\\scripts\\download_video.py", "source_location": "L104"}, {"caller_nid": "download_video_main", "callee": "add_argument", "source_file": "skills\\video-downloader\\scripts\\download_video.py", "source_location": "L107"}, {"caller_nid": "download_video_main", "callee": "add_argument", "source_file": "skills\\video-downloader\\scripts\\download_video.py", "source_location": "L108"}, {"caller_nid": "download_video_main", "callee": "add_argument", "source_file": "skills\\video-downloader\\scripts\\download_video.py", "source_location": "L113"}, {"caller_nid": "download_video_main", "callee": "add_argument", "source_file": "skills\\video-downloader\\scripts\\download_video.py", "source_location": "L119"}, {"caller_nid": "download_video_main", "callee": "add_argument", "source_file": "skills\\video-downloader\\scripts\\download_video.py", "source_location": "L125"}, {"caller_nid": "download_video_main", "callee": "parse_args", "source_file": "skills\\video-downloader\\scripts\\download_video.py", "source_location": "L131"}, {"caller_nid": "download_video_main", "callee": "exit", "source_file": "skills\\video-downloader\\scripts\\download_video.py", "source_location": "L141"}]}