{"nodes": [{"id": "api_repositories_chat_repository_py", "label": "chat_repository.py", "file_type": "code", "source_file": "api\\repositories\\chat_repository.py", "source_location": "L1"}, {"id": "chat_repository_chatrepository", "label": "ChatRepository", "file_type": "code", "source_file": "api\\repositories\\chat_repository.py", "source_location": "L10"}, {"id": "chat_repository_chatrepository_init", "label": ".__init__()", "file_type": "code", "source_file": "api\\repositories\\chat_repository.py", "source_location": "L11"}, {"id": "chat_repository_chatrepository_execute", "label": "._execute()", "file_type": "code", "source_file": "api\\repositories\\chat_repository.py", "source_location": "L14"}, {"id": "chat_repository_chatrepository_create_chat", "label": ".create_chat()", "file_type": "code", "source_file": "api\\repositories\\chat_repository.py", "source_location": "L19"}, {"id": "chat_repository_chatrepository_get_user_chats", "label": ".get_user_chats()", "file_type": "code", "source_file": "api\\repositories\\chat_repository.py", "source_location": "L33"}, {"id": "chat_repository_chatrepository_get_chat", "label": ".get_chat()", "file_type": "code", "source_file": "api\\repositories\\chat_repository.py", "source_location": "L59"}, {"id": "chat_repository_chatrepository_update_chat_timestamp", "label": ".update_chat_timestamp()", "file_type": "code", "source_file": "api\\repositories\\chat_repository.py", "source_location": "L71"}, {"id": "chat_repository_chatrepository_archive_chat", "label": ".archive_chat()", "file_type": "code", "source_file": "api\\repositories\\chat_repository.py", "source_location": "L81"}, {"id": "chat_repository_chatrepository_create_message", "label": ".create_message()", "file_type": "code", "source_file": "api\\repositories\\chat_repository.py", "source_location": "L94"}, {"id": "chat_repository_chatrepository_get_chat_messages", "label": ".get_chat_messages()", "file_type": "code", "source_file": "api\\repositories\\chat_repository.py", "source_location": "L116"}, {"id": "chat_repository_rationale_1", "label": "Database access layer for chats and messages with proper RLS support", "file_type": "rationale", "source_file": "api\\repositories\\chat_repository.py", "source_location": "L1"}, {"id": "chat_repository_rationale_15", "label": "Run blocking Supabase execute() off the event loop.", "file_type": "rationale", "source_file": "api\\repositories\\chat_repository.py", "source_location": "L15"}, {"id": "chat_repository_rationale_20", "label": "Create new chat thread", "file_type": "rationale", "source_file": "api\\repositories\\chat_repository.py", "source_location": "L20"}, {"id": "chat_repository_rationale_34", "label": "Get user's chat threads with pagination", "file_type": "rationale", "source_file": "api\\repositories\\chat_repository.py", "source_location": "L34"}, {"id": "chat_repository_rationale_60", "label": "Get single chat by ID (with ownership check)", "file_type": "rationale", "source_file": "api\\repositories\\chat_repository.py", "source_location": "L60"}, {"id": "chat_repository_rationale_72", "label": "Update chat's updated_at timestamp", "file_type": "rationale", "source_file": "api\\repositories\\chat_repository.py", "source_location": "L72"}, {"id": "chat_repository_rationale_82", "label": "Archive (soft delete) a chat", "file_type": "rationale", "source_file": "api\\repositories\\chat_repository.py", "source_location": "L82"}, {"id": "chat_repository_rationale_102", "label": "Create new message in chat", "file_type": "rationale", "source_file": "api\\repositories\\chat_repository.py", "source_location": "L102"}, {"id": "chat_repository_rationale_123", "label": "Get messages for a chat with pagination", "file_type": "rationale", "source_file": "api\\repositories\\chat_repository.py", "source_location": "L123"}], "edges": [{"source": "api_repositories_chat_repository_py", "target": "asyncio", "relation": "imports", "confidence": "EXTRACTED", "source_file": "api\\repositories\\chat_repository.py", "source_location": "L4", "weight": 1.0}, {"source": "api_repositories_chat_repository_py", "target": "typing", "relation": "imports_from", "confidence": "EXTRACTED", "source_file": "api\\repositories\\chat_repository.py", "source_location": "L5", "weight": 1.0}, {"source": "api_repositories_chat_repository_py", "target": "datetime", "relation": "imports_from", "confidence": "EXTRACTED", "source_file": "api\\repositories\\chat_repository.py", "source_location": "L6", "weight": 1.0}, {"source": "api_repositories_chat_repository_py", "target": "uuid", "relation": "imports_from", "confidence": "EXTRACTED", "source_file": "api\\repositories\\chat_repository.py", "source_location": "L7", "weight": 1.0}, {"source": "api_repositories_chat_repository_py", "target": "supabase", "relation": "imports_from", "confidence": "EXTRACTED", "source_file": "api\\repositories\\chat_repository.py", "source_location": "L8", "weight": 1.0}, {"source": "api_repositories_chat_repository_py", "target": "chat_repository_chatrepository", "relation": "contains", "confidence": "EXTRACTED", "source_file": "api\\repositories\\chat_repository.py", "source_location": "L10", "weight": 1.0}, {"source": "chat_repository_chatrepository", "target": "chat_repository_chatrepository_init", "relation": "method", "confidence": "EXTRACTED", "source_file": "api\\repositories\\chat_repository.py", "source_location": "L11", "weight": 1.0}, {"source": "chat_repository_chatrepository", "target": "chat_repository_chatrepository_execute", "relation": "method", "confidence": "EXTRACTED", "source_file": "api\\repositories\\chat_repository.py", "source_location": "L14", "weight": 1.0}, {"source": "chat_repository_chatrepository", "target": "chat_repository_chatrepository_create_chat", "relation": "method", "confidence": "EXTRACTED", "source_file": "api\\repositories\\chat_repository.py", "source_location": "L19", "weight": 1.0}, {"source": "chat_repository_chatrepository", "target": "chat_repository_chatrepository_get_user_chats", "relation": "method", "confidence": "EXTRACTED", "source_file": "api\\repositories\\chat_repository.py", "source_location": "L33", "weight": 1.0}, {"source": "chat_repository_chatrepository", "target": "chat_repository_chatrepository_get_chat", "relation": "method", "confidence": "EXTRACTED", "source_file": "api\\repositories\\chat_repository.py", "source_location": "L59", "weight": 1.0}, {"source": "chat_repository_chatrepository", "target": "chat_repository_chatrepository_update_chat_timestamp", "relation": "method", "confidence": "EXTRACTED", "source_file": "api\\repositories\\chat_repository.py", "source_location": "L71", "weight": 1.0}, {"source": "chat_repository_chatrepository", "target": "chat_repository_chatrepository_archive_chat", "relation": "method", "confidence": "EXTRACTED", "source_file": "api\\repositories\\chat_repository.py", "source_location": "L81", "weight": 1.0}, {"source": "chat_repository_chatrepository", "target": "chat_repository_chatrepository_create_message", "relation": "method", "confidence": "EXTRACTED", "source_file": "api\\repositories\\chat_repository.py", "source_location": "L94", "weight": 1.0}, {"source": "chat_repository_chatrepository", "target": "chat_repository_chatrepository_get_chat_messages", "relation": "method", "confidence": "EXTRACTED", "source_file": "api\\repositories\\chat_repository.py", "source_location": "L116", "weight": 1.0}, {"source": "chat_repository_chatrepository_create_chat", "target": "chat_repository_chatrepository_execute", "relation": "calls", "confidence": "EXTRACTED", "source_file": "api\\repositories\\chat_repository.py", "source_location": "L30", "weight": 1.0}, {"source": "chat_repository_chatrepository_get_user_chats", "target": "chat_repository_chatrepository_execute", "relation": "calls", "confidence": "EXTRACTED", "source_file": "api\\repositories\\chat_repository.py", "source_location": "L45", "weight": 1.0}, {"source": "chat_repository_chatrepository_get_chat", "target": "chat_repository_chatrepository_execute", "relation": "calls", "confidence": "EXTRACTED", "source_file": "api\\repositories\\chat_repository.py", "source_location": "L62", "weight": 1.0}, {"source": "chat_repository_chatrepository_update_chat_timestamp", "target": "chat_repository_chatrepository_execute", "relation": "calls", "confidence": "EXTRACTED", "source_file": "api\\repositories\\chat_repository.py", "source_location": "L74", "weight": 1.0}, {"source": "chat_repository_chatrepository_archive_chat", "target": "chat_repository_chatrepository_execute", "relation": "calls", "confidence": "EXTRACTED", "source_file": "api\\repositories\\chat_repository.py", "source_location": "L84", "weight": 1.0}, {"source": "chat_repository_chatrepository_create_message", "target": "chat_repository_chatrepository_execute", "relation": "calls", "confidence": "EXTRACTED", "source_file": "api\\repositories\\chat_repository.py", "source_location": "L113", "weight": 1.0}, {"source": "chat_repository_chatrepository_get_chat_messages", "target": "chat_repository_chatrepository_get_chat", "relation": "calls", "confidence": "EXTRACTED", "source_file": "api\\repositories\\chat_repository.py", "source_location": "L125", "weight": 1.0}, {"source": "chat_repository_chatrepository_get_chat_messages", "target": "chat_repository_chatrepository_execute", "relation": "calls", "confidence": "EXTRACTED", "source_file": "api\\repositories\\chat_repository.py", "source_location": "L139", "weight": 1.0}, {"source": "chat_repository_rationale_1", "target": "api_repositories_chat_repository_py", "relation": "rationale_for", "confidence": "EXTRACTED", "source_file": "api\\repositories\\chat_repository.py", "source_location": "L1", "weight": 1.0}, {"source": "chat_repository_rationale_15", "target": "chat_repository_chatrepository_execute", "relation": "rationale_for", "confidence": "EXTRACTED", "source_file": "api\\repositories\\chat_repository.py", "source_location": "L15", "weight": 1.0}, {"source": "chat_repository_rationale_20", "target": "chat_repository_chatrepository_create_chat", "relation": "rationale_for", "confidence": "EXTRACTED", "source_file": "api\\repositories\\chat_repository.py", "source_location": "L20", "weight": 1.0}, {"source": "chat_repository_rationale_34", "target": "chat_repository_chatrepository_get_user_chats", "relation": "rationale_for", "confidence": "EXTRACTED", "source_file": "api\\repositories\\chat_repository.py", "source_location": "L34", "weight": 1.0}, {"source": "chat_repository_rationale_60", "target": "chat_repository_chatrepository_get_chat", "relation": "rationale_for", "confidence": "EXTRACTED", "source_file": "api\\repositories\\chat_repository.py", "source_location": "L60", "weight": 1.0}, {"source": "chat_repository_rationale_72", "target": "chat_repository_chatrepository_update_chat_timestamp", "relation": "rationale_for", "confidence": "EXTRACTED", "source_file": "api\\repositories\\chat_repository.py", "source_location": "L72", "weight": 1.0}, {"source": "chat_repository_rationale_82", "target": "chat_repository_chatrepository_archive_chat", "relation": "rationale_for", "confidence": "EXTRACTED", "source_file": "api\\repositories\\chat_repository.py", "source_location": "L82", "weight": 1.0}, {"source": "chat_repository_rationale_102", "target": "chat_repository_chatrepository_create_message", "relation": "rationale_for", "confidence": "EXTRACTED", "source_file": "api\\repositories\\chat_repository.py", "source_location": "L102", "weight": 1.0}, {"source": "chat_repository_rationale_123", "target": "chat_repository_chatrepository_get_chat_messages", "relation": "rationale_for", "confidence": "EXTRACTED", "source_file": "api\\repositories\\chat_repository.py", "source_location": "L123", "weight": 1.0}], "raw_calls": [{"caller_nid": "chat_repository_chatrepository_execute", "callee": "to_thread", "source_file": "api\\repositories\\chat_repository.py", "source_location": "L16"}, {"caller_nid": "chat_repository_chatrepository_create_chat", "callee": "str", "source_file": "api\\repositories\\chat_repository.py", "source_location": "L22"}, {"caller_nid": "chat_repository_chatrepository_create_chat", "callee": "uuid4", "source_file": "api\\repositories\\chat_repository.py", "source_location": "L22"}, {"caller_nid": "chat_repository_chatrepository_create_chat", "callee": "isoformat", "source_file": "api\\repositories\\chat_repository.py", "source_location": "L25"}, {"caller_nid": "chat_repository_chatrepository_create_chat", "callee": "utcnow", "source_file": "api\\repositories\\chat_repository.py", "source_location": "L25"}, {"caller_nid": "chat_repository_chatrepository_create_chat", "callee": "isoformat", "source_file": "api\\repositories\\chat_repository.py", "source_location": "L26"}, {"caller_nid": "chat_repository_chatrepository_create_chat", "callee": "utcnow", "source_file": "api\\repositories\\chat_repository.py", "source_location": "L26"}, {"caller_nid": "chat_repository_chatrepository_create_chat", "callee": "insert", "source_file": "api\\repositories\\chat_repository.py", "source_location": "L30"}, {"caller_nid": "chat_repository_chatrepository_create_chat", "callee": "table", "source_file": "api\\repositories\\chat_repository.py", "source_location": "L30"}, {"caller_nid": "chat_repository_chatrepository_get_user_chats", "callee": "range", "source_file": "api\\repositories\\chat_repository.py", "source_location": "L37"}, {"caller_nid": "chat_repository_chatrepository_get_user_chats", "callee": "order", "source_file": "api\\repositories\\chat_repository.py", "source_location": "L37"}, {"caller_nid": "chat_repository_chatrepository_get_user_chats", "callee": "eq", "source_file": "api\\repositories\\chat_repository.py", "source_location": "L37"}, {"caller_nid": "chat_repository_chatrepository_get_user_chats", "callee": "eq", "source_file": "api\\repositories\\chat_repository.py", "source_location": "L37"}, {"caller_nid": "chat_repository_chatrepository_get_user_chats", "callee": "select", "source_file": "api\\repositories\\chat_repository.py", "source_location": "L37"}, {"caller_nid": "chat_repository_chatrepository_get_user_chats", "callee": "table", "source_file": "api\\repositories\\chat_repository.py", "source_location": "L37"}, {"caller_nid": "chat_repository_chatrepository_get_user_chats", "callee": "eq", "source_file": "api\\repositories\\chat_repository.py", "source_location": "L50"}, {"caller_nid": "chat_repository_chatrepository_get_user_chats", "callee": "eq", "source_file": "api\\repositories\\chat_repository.py", "source_location": "L50"}, {"caller_nid": "chat_repository_chatrepository_get_user_chats", "callee": "select", "source_file": "api\\repositories\\chat_repository.py", "source_location": "L50"}, {"caller_nid": "chat_repository_chatrepository_get_user_chats", "callee": "table", "source_file": "api\\repositories\\chat_repository.py", "source_location": "L50"}, {"caller_nid": "chat_repository_chatrepository_get_chat", "callee": "eq", "source_file": "api\\repositories\\chat_repository.py", "source_location": "L63"}, {"caller_nid": "chat_repository_chatrepository_get_chat", "callee": "eq", "source_file": "api\\repositories\\chat_repository.py", "source_location": "L63"}, {"caller_nid": "chat_repository_chatrepository_get_chat", "callee": "select", "source_file": "api\\repositories\\chat_repository.py", "source_location": "L63"}, {"caller_nid": "chat_repository_chatrepository_get_chat", "callee": "table", "source_file": "api\\repositories\\chat_repository.py", "source_location": "L63"}, {"caller_nid": "chat_repository_chatrepository_update_chat_timestamp", "callee": "eq", "source_file": "api\\repositories\\chat_repository.py", "source_location": "L75"}, {"caller_nid": "chat_repository_chatrepository_update_chat_timestamp", "callee": "eq", "source_file": "api\\repositories\\chat_repository.py", "source_location": "L75"}, {"caller_nid": "chat_repository_chatrepository_update_chat_timestamp", "callee": "update", "source_file": "api\\repositories\\chat_repository.py", "source_location": "L75"}, {"caller_nid": "chat_repository_chatrepository_update_chat_timestamp", "callee": "table", "source_file": "api\\repositories\\chat_repository.py", "source_location": "L75"}, {"caller_nid": "chat_repository_chatrepository_update_chat_timestamp", "callee": "isoformat", "source_file": "api\\repositories\\chat_repository.py", "source_location": "L76"}, {"caller_nid": "chat_repository_chatrepository_update_chat_timestamp", "callee": "utcnow", "source_file": "api\\repositories\\chat_repository.py", "source_location": "L76"}, {"caller_nid": "chat_repository_chatrepository_archive_chat", "callee": "eq", "source_file": "api\\repositories\\chat_repository.py", "source_location": "L85"}, {"caller_nid": "chat_repository_chatrepository_archive_chat", "callee": "eq", "source_file": "api\\repositories\\chat_repository.py", "source_location": "L85"}, {"caller_nid": "chat_repository_chatrepository_archive_chat", "callee": "update", "source_file": "api\\repositories\\chat_repository.py", "source_location": "L85"}, {"caller_nid": "chat_repository_chatrepository_archive_chat", "callee": "table", "source_file": "api\\repositories\\chat_repository.py", "source_location": "L85"}, {"caller_nid": "chat_repository_chatrepository_archive_chat", "callee": "len", "source_file": "api\\repositories\\chat_repository.py", "source_location": "L91"}, {"caller_nid": "chat_repository_chatrepository_create_message", "callee": "str", "source_file": "api\\repositories\\chat_repository.py", "source_location": "L104"}, {"caller_nid": "chat_repository_chatrepository_create_message", "callee": "uuid4", "source_file": "api\\repositories\\chat_repository.py", "source_location": "L104"}, {"caller_nid": "chat_repository_chatrepository_create_message", "callee": "isoformat", "source_file": "api\\repositories\\chat_repository.py", "source_location": "L110"}, {"caller_nid": "chat_repository_chatrepository_create_message", "callee": "utcnow", "source_file": "api\\repositories\\chat_repository.py", "source_location": "L110"}, {"caller_nid": "chat_repository_chatrepository_create_message", "callee": "insert", "source_file": "api\\repositories\\chat_repository.py", "source_location": "L113"}, {"caller_nid": "chat_repository_chatrepository_create_message", "callee": "table", "source_file": "api\\repositories\\chat_repository.py", "source_location": "L113"}, {"caller_nid": "chat_repository_chatrepository_get_chat_messages", "callee": "range", "source_file": "api\\repositories\\chat_repository.py", "source_location": "L131"}, {"caller_nid": "chat_repository_chatrepository_get_chat_messages", "callee": "order", "source_file": "api\\repositories\\chat_repository.py", "source_location": "L131"}, {"caller_nid": "chat_repository_chatrepository_get_chat_messages", "callee": "eq", "source_file": "api\\repositories\\chat_repository.py", "source_location": "L131"}, {"caller_nid": "chat_repository_chatrepository_get_chat_messages", "callee": "eq", "source_file": "api\\repositories\\chat_repository.py", "source_location": "L131"}, {"caller_nid": "chat_repository_chatrepository_get_chat_messages", "callee": "select", "source_file": "api\\repositories\\chat_repository.py", "source_location": "L131"}, {"caller_nid": "chat_repository_chatrepository_get_chat_messages", "callee": "table", "source_file": "api\\repositories\\chat_repository.py", "source_location": "L131"}, {"caller_nid": "chat_repository_chatrepository_get_chat_messages", "callee": "eq", "source_file": "api\\repositories\\chat_repository.py", "source_location": "L144"}, {"caller_nid": "chat_repository_chatrepository_get_chat_messages", "callee": "eq", "source_file": "api\\repositories\\chat_repository.py", "source_location": "L144"}, {"caller_nid": "chat_repository_chatrepository_get_chat_messages", "callee": "select", "source_file": "api\\repositories\\chat_repository.py", "source_location": "L144"}, {"caller_nid": "chat_repository_chatrepository_get_chat_messages", "callee": "table", "source_file": "api\\repositories\\chat_repository.py", "source_location": "L144"}]}