{"nodes": [{"id": "skills_slack_gif_creator_templates_pulse_py", "label": "pulse.py", "file_type": "code", "source_file": "skills\\slack-gif-creator\\templates\\pulse.py", "source_location": "L1"}, {"id": "pulse_create_pulse_animation", "label": "create_pulse_animation()", "file_type": "code", "source_file": "skills\\slack-gif-creator\\templates\\pulse.py", "source_location": "L20"}, {"id": "pulse_create_attention_pulse", "label": "create_attention_pulse()", "file_type": "code", "source_file": "skills\\slack-gif-creator\\templates\\pulse.py", "source_location": "L156"}, {"id": "pulse_create_breathing_animation", "label": "create_breathing_animation()", "file_type": "code", "source_file": "skills\\slack-gif-creator\\templates\\pulse.py", "source_location": "L188"}, {"id": "pulse_rationale_32", "label": "Create pulsing/scaling animation.      Args:         object_type: 'emoji', 'c", "file_type": "rationale", "source_file": "skills\\slack-gif-creator\\templates\\pulse.py", "source_location": "L32"}, {"id": "pulse_rationale_162", "label": "Create attention-grabbing pulse (good for emoji GIFs).      Args:         emo", "file_type": "rationale", "source_file": "skills\\slack-gif-creator\\templates\\pulse.py", "source_location": "L162"}, {"id": "pulse_rationale_198", "label": "Create slow, calming breathing animation (in and out).      Args:         obj", "file_type": "rationale", "source_file": "skills\\slack-gif-creator\\templates\\pulse.py", "source_location": "L198"}], "edges": [{"source": "skills_slack_gif_creator_templates_pulse_py", "target": "sys", "relation": "imports", "confidence": "EXTRACTED", "source_file": "skills\\slack-gif-creator\\templates\\pulse.py", "source_location": "L8", "weight": 1.0}, {"source": "skills_slack_gif_creator_templates_pulse_py", "target": "pathlib", "relation": "imports_from", "confidence": "EXTRACTED", "source_file": "skills\\slack-gif-creator\\templates\\pulse.py", "source_location": "L9", "weight": 1.0}, {"source": "skills_slack_gif_creator_templates_pulse_py", "target": "math", "relation": "imports", "confidence": "EXTRACTED", "source_file": "skills\\slack-gif-creator\\templates\\pulse.py", "source_location": "L10", "weight": 1.0}, {"source": "skills_slack_gif_creator_templates_pulse_py", "target": "pil", "relation": "imports_from", "confidence": "EXTRACTED", "source_file": "skills\\slack-gif-creator\\templates\\pulse.py", "source_location": "L14", "weight": 1.0}, {"source": "skills_slack_gif_creator_templates_pulse_py", "target": "core_gif_builder", "relation": "imports_from", "confidence": "EXTRACTED", "source_file": "skills\\slack-gif-creator\\templates\\pulse.py", "source_location": "L15", "weight": 1.0}, {"source": "skills_slack_gif_creator_templates_pulse_py", "target": "core_frame_composer", "relation": "imports_from", "confidence": "EXTRACTED", "source_file": "skills\\slack-gif-creator\\templates\\pulse.py", "source_location": "L16", "weight": 1.0}, {"source": "skills_slack_gif_creator_templates_pulse_py", "target": "core_easing", "relation": "imports_from", "confidence": "EXTRACTED", "source_file": "skills\\slack-gif-creator\\templates\\pulse.py", "source_location": "L17", "weight": 1.0}, {"source": "skills_slack_gif_creator_templates_pulse_py", "target": "pulse_create_pulse_animation", "relation": "contains", "confidence": "EXTRACTED", "source_file": "skills\\slack-gif-creator\\templates\\pulse.py", "source_location": "L20", "weight": 1.0}, {"source": "skills_slack_gif_creator_templates_pulse_py", "target": "pulse_create_attention_pulse", "relation": "contains", "confidence": "EXTRACTED", "source_file": "skills\\slack-gif-creator\\templates\\pulse.py", "source_location": "L156", "weight": 1.0}, {"source": "skills_slack_gif_creator_templates_pulse_py", "target": "pulse_create_breathing_animation", "relation": "contains", "confidence": "EXTRACTED", "source_file": "skills\\slack-gif-creator\\templates\\pulse.py", "source_location": "L188", "weight": 1.0}, {"source": "pulse_create_attention_pulse", "target": "pulse_create_pulse_animation", "relation": "calls", "confidence": "EXTRACTED", "source_file": "skills\\slack-gif-creator\\templates\\pulse.py", "source_location": "L174", "weight": 1.0}, {"source": "pulse_create_breathing_animation", "target": "pulse_create_pulse_animation", "relation": "calls", "confidence": "EXTRACTED", "source_file": "skills\\slack-gif-creator\\templates\\pulse.py", "source_location": "L217", "weight": 1.0}, {"source": "pulse_rationale_32", "target": "pulse_create_pulse_animation", "relation": "rationale_for", "confidence": "EXTRACTED", "source_file": "skills\\slack-gif-creator\\templates\\pulse.py", "source_location": "L32", "weight": 1.0}, {"source": "pulse_rationale_162", "target": "pulse_create_attention_pulse", "relation": "rationale_for", "confidence": "EXTRACTED", "source_file": "skills\\slack-gif-creator\\templates\\pulse.py", "source_location": "L162", "weight": 1.0}, {"source": "pulse_rationale_198", "target": "pulse_create_breathing_animation", "relation": "rationale_for", "confidence": "EXTRACTED", "source_file": "skills\\slack-gif-creator\\templates\\pulse.py", "source_location": "L198", "weight": 1.0}], "raw_calls": [{"caller_nid": "pulse_create_pulse_animation", "callee": "range", "source_file": "skills\\slack-gif-creator\\templates\\pulse.py", "source_location": "L61"}, {"caller_nid": "pulse_create_pulse_animation", "callee": "create_blank_frame", "source_file": "skills\\slack-gif-creator\\templates\\pulse.py", "source_location": "L62"}, {"caller_nid": "pulse_create_pulse_animation", "callee": "sin", "source_file": "skills\\slack-gif-creator\\templates\\pulse.py", "source_location": "L69"}, {"caller_nid": "pulse_create_pulse_animation", "callee": "interpolate", "source_file": "skills\\slack-gif-creator\\templates\\pulse.py", "source_location": "L77"}, {"caller_nid": "pulse_create_pulse_animation", "callee": "interpolate", "source_file": "skills\\slack-gif-creator\\templates\\pulse.py", "source_location": "L80"}, {"caller_nid": "pulse_create_pulse_animation", "callee": "interpolate", "source_file": "skills\\slack-gif-creator\\templates\\pulse.py", "source_location": "L83"}, {"caller_nid": "pulse_create_pulse_animation", "callee": "interpolate", "source_file": "skills\\slack-gif-creator\\templates\\pulse.py", "source_location": "L86"}, {"caller_nid": "pulse_create_pulse_animation", "callee": "interpolate", "source_file": "skills\\slack-gif-creator\\templates\\pulse.py", "source_location": "L95"}, {"caller_nid": "pulse_create_pulse_animation", "callee": "interpolate", "source_file": "skills\\slack-gif-creator\\templates\\pulse.py", "source_location": "L97"}, {"caller_nid": "pulse_create_pulse_animation", "callee": "interpolate", "source_file": "skills\\slack-gif-creator\\templates\\pulse.py", "source_location": "L104"}, {"caller_nid": "pulse_create_pulse_animation", "callee": "interpolate", "source_file": "skills\\slack-gif-creator\\templates\\pulse.py", "source_location": "L107"}, {"caller_nid": "pulse_create_pulse_animation", "callee": "sin", "source_file": "skills\\slack-gif-creator\\templates\\pulse.py", "source_location": "L111"}, {"caller_nid": "pulse_create_pulse_animation", "callee": "int", "source_file": "skills\\slack-gif-creator\\templates\\pulse.py", "source_location": "L117"}, {"caller_nid": "pulse_create_pulse_animation", "callee": "draw_emoji_enhanced", "source_file": "skills\\slack-gif-creator\\templates\\pulse.py", "source_location": "L118"}, {"caller_nid": "pulse_create_pulse_animation", "callee": "get", "source_file": "skills\\slack-gif-creator\\templates\\pulse.py", "source_location": "L123"}, {"caller_nid": "pulse_create_pulse_animation", "callee": "int", "source_file": "skills\\slack-gif-creator\\templates\\pulse.py", "source_location": "L128"}, {"caller_nid": "pulse_create_pulse_animation", "callee": "draw_circle", "source_file": "skills\\slack-gif-creator\\templates\\pulse.py", "source_location": "L129"}, {"caller_nid": "pulse_create_pulse_animation", "callee": "get", "source_file": "skills\\slack-gif-creator\\templates\\pulse.py", "source_location": "L138"}, {"caller_nid": "pulse_create_pulse_animation", "callee": "int", "source_file": "skills\\slack-gif-creator\\templates\\pulse.py", "source_location": "L139"}, {"caller_nid": "pulse_create_pulse_animation", "callee": "draw_text_with_outline", "source_file": "skills\\slack-gif-creator\\templates\\pulse.py", "source_location": "L140"}, {"caller_nid": "pulse_create_pulse_animation", "callee": "get", "source_file": "skills\\slack-gif-creator\\templates\\pulse.py", "source_location": "L142"}, {"caller_nid": "pulse_create_pulse_animation", "callee": "get", "source_file": "skills\\slack-gif-creator\\templates\\pulse.py", "source_location": "L145"}, {"caller_nid": "pulse_create_pulse_animation", "callee": "get", "source_file": "skills\\slack-gif-creator\\templates\\pulse.py", "source_location": "L146"}, {"caller_nid": "pulse_create_pulse_animation", "callee": "append", "source_file": "skills\\slack-gif-creator\\templates\\pulse.py", "source_location": "L151"}]}